mm_jinja/__init__.py
mm_jinja/filters.py
mm_jinja/globals.py
mm_jinja/jinja.py
mm_jinja/py.typed
mm_jinja-0.0.5.dist-info/METADATA
mm_jinja-0.0.5.dist-info/WHEEL
mm_jinja-0.0.5.dist-info/RECORD
