Metadata-Version: 2.4
Name: mm-jinja
Version: 0.0.5
Requires-Python: >=3.12
Requires-Dist: jinja2>=3.1.6
